README.md
setup.py
social_phi/__init__.py
social_phi/phi.py
social_phi/signal.py
social_phi/utils.py
social_phi.egg-info/PKG-INFO
social_phi.egg-info/SOURCES.txt
social_phi.egg-info/dependency_links.txt
social_phi.egg-info/requires.txt
social_phi.egg-info/top_level.txt